package_name/__init__.py
image_processing_thaiza_dantas_tools-0.0.1.dist-info/METADATA
image_processing_thaiza_dantas_tools-0.0.1.dist-info/WHEEL
image_processing_thaiza_dantas_tools-0.0.1.dist-info/top_level.txt
image_processing_thaiza_dantas_tools-0.0.1.dist-info/RECORD
