Metadata-Version: 2.4
Name: image_processing_thaiza_dantas_tools
Version: 0.0.1
Summary: Image Processing Package using Skimage
Home-page: https://github.com/thaiza-d/image_processing_thaiza_dantas_tools
Author: Thaiza
Requires-Python: >=3.5
Dynamic: author
Dynamic: description
Dynamic: description-content-type
Dynamic: home-page
Dynamic: requires-python
Dynamic: summary
